IsoScore/IsoScore.py
IsoScore/__init__.py
IsoScore-2.0.1.dist-info/LICENSE
IsoScore-2.0.1.dist-info/METADATA
IsoScore-2.0.1.dist-info/WHEEL
IsoScore-2.0.1.dist-info/top_level.txt
IsoScore-2.0.1.dist-info/RECORD
