Metadata-Version: 2.1
Name: IsoScore
Version: 2.0.1
Summary: IsoScore is the first tool available in the literature that accurately measures isotropy in embedding space.
Home-page: https://github.com/bcbi-edu/p_eickhoff_isoscore
Author: William Rudman
Author-email: william_rudman@brown.edu
Classifier: Programming Language :: Python :: 3
Classifier: License :: OSI Approved :: MIT License
Classifier: Operating System :: OS Independent
Requires-Python: >=3.6
License-File: LICENSE
